pygame_grid/__init__.py
pygame_grid-0.0.3.dist-info/LICENSE
pygame_grid-0.0.3.dist-info/METADATA
pygame_grid-0.0.3.dist-info/WHEEL
pygame_grid-0.0.3.dist-info/top_level.txt
pygame_grid-0.0.3.dist-info/RECORD
