Metadata-Version: 2.1
Name: pygame-grid
Version: 0.0.3
Summary: Add a grid to your pygame screen.
Author-email: Casey Devet <cjdevet@gmail.com>
License: Copyright 2021 Casey Devet
Project-URL: Homepage, https://github.com/mrdevet/pygame-grid
Keywords: pygame,grid
Classifier: License :: OSI Approved :: MIT License
Classifier: Programming Language :: Python :: 3
Requires-Python: >=3
License-File: LICENSE
